mombai/__init__.py
mombai/activations/__init__.py
mombai/activations/splines.py
mombai/layers/__init__.py
mombai/layers/kan.py
mombai/layers/multi_activation.py
mombai-2.0.3.dist-info/LICENSE
mombai-2.0.3.dist-info/METADATA
mombai-2.0.3.dist-info/WHEEL
mombai-2.0.3.dist-info/top_level.txt
mombai-2.0.3.dist-info/RECORD
