Metadata-Version: 2.1
Name: mombai
Version: 2.0.3
Summary: A deep learning library for advanced neural network layers.
Home-page: https://github.com/joaquinsc999/mombai
Author: Joaquín Francisco Solórzano Corea
Author-email: joaquinscorea@gmail.com
Classifier: Programming Language :: Python :: 3
Classifier: License :: OSI Approved :: MIT License
Classifier: Operating System :: OS Independent
Requires-Python: >=3.6
License-File: LICENSE
Requires-Dist: tensorflow>=2.0
